dingent/__init__.py
dingent/cli/__init__.py
dingent/cli/assets.py
dingent/cli/cli.py
dingent/core/__init__.py
dingent/core/config.py
dingent/core/context.py
dingent/core/paths.py
dingent/core/types.py
dingent/core/utils.py
dingent/core/assistants/__init__.py
dingent/core/assistants/assistant.py
dingent/core/assistants/assistant_factory.py
dingent/core/assistants/schemas.py
dingent/core/db/__init__.py
dingent/core/db/models.py
dingent/core/db/session.py
dingent/core/db/types.py
dingent/core/db/crud/__init__.py
dingent/core/db/crud/assistant.py
dingent/core/db/crud/plugin.py
dingent/core/db/crud/user.py
dingent/core/db/crud/workflow.py
dingent/core/db/crud/workspace.py
dingent/core/llms/__init__.py
dingent/core/llms/analytics_manager.py
dingent/core/llms/resolver.py
dingent/core/llms/schemas.py
dingent/core/llms/service.py
dingent/core/logs/__init__.py
dingent/core/logs/log_manager.py
dingent/core/logs/schemas.py
dingent/core/plugins/__init__.py
dingent/core/plugins/market_service.py
dingent/core/plugins/plugin.py
dingent/core/plugins/plugin_manager.py
dingent/core/plugins/plugin_registry.py
dingent/core/plugins/schemas.py
dingent/core/security/__init__.py
dingent/core/security/crypto.py
dingent/core/security/permissions.py
dingent/core/security/utils.py
dingent/core/workflows/__init__.py
dingent/core/workflows/graph_factory.py
dingent/core/workflows/presets.py
dingent/core/workflows/schemas.py
dingent/core/workspaces/__init__.py
dingent/core/workspaces/schemas.py
dingent/engine/__init__.py
dingent/engine/agents/__init__.py
dingent/engine/agents/messages.py
dingent/engine/agents/simple_agent.py
dingent/engine/agents/state.py
dingent/engine/agents/tools.py
dingent/engine/factories/__init__.py
dingent/engine/factories/swarm.py
dingent/server/__init__.py
dingent/server/app.py
dingent/server/main.py
dingent/server/api/__init__.py
dingent/server/api/dependencies.py
dingent/server/api/schemas.py
dingent/server/api/routers/__init__.py
dingent/server/api/routers/auth.py
dingent-0.5.11.dist-info/METADATA
dingent-0.5.11.dist-info/WHEEL
dingent-0.5.11.dist-info/entry_points.txt
dingent-0.5.11.dist-info/licenses/LICENSE
dingent-0.5.11.dist-info/RECORD
