Metadata-Version: 2.4
Name: dingent
Version: 0.5.11
Summary: AI agent framework
Author-email: saya <c3313433633@gmail.com>
License-File: LICENSE
Requires-Python: <3.14,>=3.12
Requires-Dist: aiohttp>=3.13.3
Requires-Dist: aiosqlite>=0.21.0
Requires-Dist: async-lru>=2.0.5
Requires-Dist: cookiecutter>=2.6.0
Requires-Dist: copilotkit>=0.1.56
Requires-Dist: fastapi[all]>=0.115.14
Requires-Dist: fastmcp>=2.2.0
Requires-Dist: fsspec>=2025.12.0
Requires-Dist: google-genai>=1.32.0
Requires-Dist: keyring>=25.6.0
Requires-Dist: langchain-litellm>=0.2.2
Requires-Dist: langchain-mcp-adapters>=0.0.11
Requires-Dist: langchain>=0.3.23
Requires-Dist: langgraph-api>=0.0.21
Requires-Dist: langgraph-checkpoint-sqlite>=2.0.11
Requires-Dist: langgraph-cli[inmem]>=0.1.73
Requires-Dist: langgraph-swarm>=0.0.12
Requires-Dist: langgraph>=0.6.3
Requires-Dist: litellm>=1.76.1
Requires-Dist: loguru>=0.7.3
Requires-Dist: nodejs-wheel>=22.18.0
Requires-Dist: numpy>=2.3.0
Requires-Dist: psutil>=7.0.0
Requires-Dist: pwdlib[argon2]>=0.3.0
Requires-Dist: pycasbin>=2.2.0
Requires-Dist: pydantic-settings<3.0.0,>=2.4.0
Requires-Dist: python-jose[cryptography]>=3.5.0
Requires-Dist: sqlmodel>=0.0.25
Requires-Dist: toml>=0.10.2
Requires-Dist: tomlkit>=0.13.3
Requires-Dist: typer>=0.16.0
